pyman/Action.py
pyman/Actions.py
pyman/Doc.py
pyman/Git.py
pyman/Main.py
pyman/NoseTest.py
pyman/Page.py
pyman/PyPi.py
pyman/Screen.py
pyman/Webpack.py
pyman/__init__.py
pyman-0.1.3.dist-info/METADATA
pyman-0.1.3.dist-info/RECORD
pyman-0.1.3.dist-info/WHEEL
pyman-0.1.3.dist-info/top_level.txt
