Metadata-Version: 2.1
Name: pyman
Version: 0.1.3
Summary: A CLI for managing python projects
Home-page: https://github.com/MarkLark/pyman
Author: Mark Pittaway
Author-email: mark.pittaway@mlit.net.au
License: MIT
Platform: any
Classifier: Development Status :: 3 - Alpha
Classifier: Intended Audience :: Developers
Classifier: Environment :: Console
Classifier: Topic :: Software Development :: Testing
Classifier: Topic :: Software Development :: Build Tools
Classifier: Topic :: Software Development :: User Interfaces
Classifier: License :: OSI Approved :: MIT License
Classifier: Programming Language :: Python
Classifier: Programming Language :: Python :: 2
Classifier: Programming Language :: Python :: 2.6
Classifier: Programming Language :: Python :: 2.7
Classifier: Programming Language :: Python :: 3
Classifier: Programming Language :: Python :: 3.3
Classifier: Programming Language :: Python :: 3.4
Classifier: Programming Language :: Python :: 3.5
Classifier: Programming Language :: Python :: 3.6
Classifier: Operating System :: POSIX :: Linux
